{
    "_coeffs": [
        -1.6809032710186434e-11,
        5.837612541969651e-08,
        -9.72668459482145e-07
    ],
    "datasets": [
        "dataset-carbon-dioxide-lienhard2018.csv"
    ],
    "display_symbol": "\\mu",
    "material": "Carbon Dioxide",
    "property": "Dynamic Viscosity",
    "py/object": "auxi.tools.materialphysicalproperties.polynomial.PolynomialModelT",
    "references": null,
    "state_schema": {
        "T": {
            "max": 600.0,
            "min": 220.0,
            "required": true,
            "type": "float"
        }
    },
    "state_validator": {
        "_Validator__config": {
            "schema": {
                "T": {
                    "max": 600.0,
                    "min": 220.0,
                    "required": true,
                    "type": "float"
                }
            }
        },
        "_current": {
            "T": {
                "py/reduce": [
                    {
                        "py/function": "numpy.core.multiarray.scalar"
                    },
                    {
                        "py/tuple": [
                            {
                                "py/reduce": [
                                    {
                                        "py/type": "numpy.dtype"
                                    },
                                    {
                                        "py/tuple": [
                                            "f8",
                                            0,
                                            1
                                        ]
                                    },
                                    {
                                        "py/tuple": [
                                            3,
                                            "<",
                                            null,
                                            null,
                                            null,
                                            -1,
                                            -1,
                                            0
                                        ]
                                    },
                                    null,
                                    null
                                ]
                            },
                            {
                                "py/b64": "AAAAAADAgkA=\n"
                            }
                        ]
                    },
                    null,
                    null,
                    null
                ]
            }
        },
        "_errors": {},
        "allow_unknown": false,
        "document": {
            "T": {
                "py/id": 4
            }
        },
        "ignore_none_values": false,
        "py/object": "cerberus.cerberus.Validator",
        "schema": {
            "T": {
                "max": 600.0,
                "min": 220.0,
                "required": true,
                "type": "float"
            }
        },
        "transparent_schema_rules": false,
        "update": false
    },
    "symbol": "mu",
    "units": "kg/m/s"
}